exmecheva/Eva_ACT.py
exmecheva/Eva_ATT.py
exmecheva/Eva_TBT.py
exmecheva/__init__.py
exmecheva/eva.py
exmecheva/bending/__init__.py
exmecheva/bending/attr_bgl.py
exmecheva/bending/bfunc_class.py
exmecheva/bending/bfunc_com.py
exmecheva/bending/bfunc_fse.py
exmecheva/bending/evaluation.py
exmecheva/bending/fitting.py
exmecheva/bending/opt_mps.py
exmecheva/bending/plotting.py
exmecheva/common/__init__.py
exmecheva/common/analyze.py
exmecheva/common/eva_opt_hand.py
exmecheva/common/fitting.py
exmecheva/common/helper.py
exmecheva/common/list_ops.py
exmecheva/common/loadnsave.py
exmecheva/common/mc_char.py
exmecheva/common/mc_man.py
exmecheva/common/mc_yield.py
exmecheva/common/output.py
exmecheva/common/pd_ext.py
exmecheva/common/plotting.py
exmecheva/common/stat_ext.py
exmecheva-0.1.2.dist-info/METADATA
exmecheva-0.1.2.dist-info/WHEEL
exmecheva-0.1.2.dist-info/licenses/LICENSE
exmecheva-0.1.2.dist-info/RECORD
