Metadata-Version: 2.3
Name: ExMechEva
Version: 0.1.2
Summary: Evaluation of experimental mechanics data
Project-URL: Homepage, https://github.com/MarcGebhardt/ExMechEva
Project-URL: Issues, https://github.com/MarcGebhardt/ExMechEva/issues
Project-URL: Source, https://github.com/MarcGebhardt/ExMechEva
Project-URL: Changelog, https://github.com/MarcGebhardt/ExMechEva/CHANGELOG.md
Author-email: Marc Gebhardt <marcgebhardt.dev+gheme@gmail.com>
Maintainer-email: Marc Gebhardt <marcgebhardt.dev+gheme@gmail.com>
License: MIT License
License-File: LICENSE
Keywords: axial compression,axial tension,biomechanics,experimental mechanics,three point bending
Classifier: Development Status :: 3 - Alpha
Classifier: Intended Audience :: Developers
Classifier: Intended Audience :: Science/Research
Classifier: License :: OSI Approved :: MIT License
Classifier: Programming Language :: Python
Classifier: Programming Language :: Python :: 3
Classifier: Programming Language :: Python :: 3 :: Only
Classifier: Programming Language :: Python :: 3.7
Requires-Python: >=3.7.10
Requires-Dist: lmfit>=1.0.2
Requires-Dist: matplotlib>=3.3.4
Requires-Dist: numpy>=1.20.3
Requires-Dist: pandas>=1.3.0
Requires-Dist: scikit-posthocs>=0.7.0
Requires-Dist: scipy>=1.6.2
Requires-Dist: seaborn>=0.11.1
Requires-Dist: statsmodels>=0.12.2
Requires-Dist: sympy>=1.8
Requires-Dist: tqdm>=4.61.2
Requires-Dist: vg>=1.9.0
